<?xml version="1.0"?>
<?xml-stylesheet href="staff.css" type="text/css"?>
<Staff>
   <notes>
      <![CDATA[
   There are over 85 employees at Biotech. This document contains data on each employee's
   status, department affiliation, years employed, social security number, health plane, and
   salary.
   ]]>
   </notes>

   <Employee1:emp xmlns:Employee1="https://www.emp1.com">
      <Employee1:Name>Janice Richardson</Employee1:Name>
      <Employee1:Status>Fulltime</Employee1:Status>
      <Employee1:Department>Sales</Employee1:Department>
      <Employee1:Years>5</Employee1:Years>
      <Employee1:Years>370-16-3631</Employee1:Years>
      <Employee1:Health>Standard Single</Employee1:Health>
      <Employee1:Salary>$42,500</Employee1:Salary>
   </Employee1:emp>

   <Employee2:emp xmlns:Employee2="https://www.emp2.com">
      <Employee2:Name>Alan Wu</Employee2:Name>
      <Employee2:Status>Fulltime</Employee2:Status>
      <Employee2:Department>Research</Employee2:Department>
      <Employee2:Years>2</Employee2:Years>
      <Employee2:SS>385-22-3311</Employee2:SS>
      <Employee2:Health>Standard Married</Employee2:Health>
      <Employee2:Salary>$52,800</Employee2:Salary>
   </Employee2:emp>

   <Employee3:emp xmlns:Employee3="https://www.emp3.com">
      <Name>Walter Bright</Name>
      <Status>Part-time</Status>
      <Department>Sales</Department>
      <Years>1</Years>
      <SS>310-46-8933</SS>
      <Health>None</Health>
      <Salary>$22,500</Salary>
   </Employee3:emp>

   <Employee4:emp xmlns:Employee4="https://www.emp4.com">
      <Employee4:Name>Cindy Jacques</Employee4:Name>
      <Employee4:Status>Fulltime</Employee4:Status>
      <Employee4:Department>Management</Employee4:Department>
      <Employee4:Years>15</Employee4:Years>
      <Employee4:SS>301-88-8891</Employee4:SS>
      <Employee4:Health>Bonus Married</Employee4:Health>
      <Employee4:Salary>$68,400</Employee4:Salary>
   </Employee4:emp>

   <Employee5:emp xmlns:Employee5="https://www.emp5.com">
      <Employee5:Name>Kelly Sanchez</Employee5:Name>
      <Employee5:Status>Fulltime</Employee5:Status>
      <Employee5:Department>Sales</Employee5:Department>
      <Employee5:Years>3</Employee5:Years>
      <Employee5:SS>312-22-4817</Employee5:SS>
      <Employee5:Health>Standard Single</Employee5:Health>
      <Employee5:Salary>$38,500</Employee5:Salary>
   </Employee5:emp>

   <Employee6:emp xmlns:Employee6="https://www.emp6.com">
      <Employee6:Name>Larry Unwin</Employee6:Name>
      <Employee6:Status>Fulltime</Employee6:Status>
      <Employee6:Department>Finance</Employee6:Department>
      <Employee6:Years>8</Employee6:Years>
      <Employee6:SS>325-99-5515</Employee6:SS>
      <Employee6:Health>Standard Married</Employee6:Health>
      <Employee6:Salary>$49,300</Employee6:Salary>
   </Employee6:emp>

   <Employee7:emp xmlns:Employee7="https://www.emp7.com">
      <Employee7:Name>Carl Li</Employee7:Name>
      <Employee7:Status>Fulltime</Employee7:Status>
      <Employee7:Department>Research</Employee7:Department>
      <Employee7:Years>3</Employee7:Years>
      <Employee7:SS>353-56-5652</Employee7:SS>
      <Employee7:Health>Standard Single</Employee7:Health>
      <Employee7:Salary>$55,500</Employee7:Salary>
   </Employee7:emp>

   <Employee8:emp xmlns:Employee8="https://www.emp8.com">
      <Employee8:Name>Diane Lane</Employee8:Name>
      <Employee8:Status>Part-time</Employee8:Status>
      <Employee8:Department>Finance</Employee8:Department>
      <Employee8:Years>1</Employee8:Years>
      <Employee8:SS>381-29-4533</Employee8:SS>
      <Employee8:Health>None</Employee8:Health>
      <Employee8:Salary>$25,100</Employee8:Salary>
   </Employee8:emp>

   <Employee9:emp xmlns:Employee9="https://www.emp9.com">
      <Employee9:Name>Harold Wilkes</Employee9:Name>
      <Employee9:Status>Fulltime</Employee9:Status>
      <Employee9:Department>Sales Finance</Employee9:Department>
      <Employee9:Years>5</Employee9:Years>
      <Employee9:SS>372-32-3232</Employee9:SS>
      <Employee9:Health>Standard Married</Employee9:Health>
      <Employee9:Salary>$44,500</Employee9:Salary>
   </Employee9:emp>

   <Employee10:emp xmlns:Employee10="https://www.emp10.com">
      <Employee10:Name>Robert Breznski</Employee10:Name>
      <Employee10:Status>Fulltime</Employee10:Status>
      <Employee10:Department>Sales</Employee10:Department>
      <Employee10:Years>10</Employee10:Years>
      <Employee10:SS>374-46-3234</Employee10:SS>
      <Employee10:Health>Bonus Married</Employee10:Health>
      <Employee10:Salary>$49,900</Employee10:Salary>
   </Employee10:emp>

   <Employee11:emp xmlns:Employee11="https://www.emp11.com">
      <Employee11:Name>Karen Dawes</Employee11:Name>
      <Employee11:Status>Fulltime</Employee11:Status>
      <Employee11:Department>Management</Employee11:Department>
      <Employee11:Years>12</Employee11:Years>
      <Employee11:SS>365-50-2030</Employee11:SS>
      <Employee11:Health>Bonus Single</Employee11:Health>
      <Employee11:Salary>$82,500</Employee11:Salary>
   </Employee11:emp>

   <Employee12:emp xmlns:Employee12="https://www.emp12.com">
      <Employee12:Name>Olivia Wills</Employee12:Name>
      <Employee12:Status>Fulltime</Employee12:Status>
      <Employee12:Department>Research</Employee12:Department>
      <Employee12:Years>2</Employee12:Years>
      <Employee12:SS>372-22-3232</Employee12:SS>
      <Employee12:Health>Standard Married</Employee12:Health>
      <Employee12:Salary>$52,300</Employee12:Salary>
   </Employee12:emp>

   <Employee13:emp xmlns:Employee13="https://www.emp13.com">
      <Employee13:Name>Carl Levine</Employee13:Name>
      <Employee13:Status>Fulltime</Employee13:Status>
      <Employee13:Department>Sales</Employee13:Department>
      <Employee13:Years>1</Employee13:Years>
      <Employee13:SS>379-96-9639</Employee13:SS>
      <Employee13:Health>Standard Single</Employee13:Health>
      <Employee13:Salary>$49,500</Employee13:Salary>
   </Employee13:emp>

   <Employee14:emp xmlns:Employee14="https://www.emp14.com">
      <Employee14:Name>Bert Browne</Employee14:Name>
      <Employee14:Status>Fulltime</Employee14:Status>
      <Employee14:Department>Research</Employee14:Department>
      <Employee14:Year>4</Employee14:Year>
      <Employee14:SS>364-46-4643</Employee14:SS>
      <Employee14:Health>Standard Married</Employee14:Health>
      <Employee14:Salary>$52,500</Employee14:Salary>
   </Employee14:emp>

   <Employee15:emp xmlns:Employee15="https://www.emp15.com">
      <Employee15:Name>Jill Whyte</Employee15:Name>
      <Employee15:Status>Part-time</Employee15:Status>
      <Employee15:Department>Sales</Employee15:Department>
      <Employee15:Years>1</Employee15:Years>
      <Employee15:SS>375-15-5635</Employee15:SS>
      <Employee15:Health>None</Employee15:Health>
      <Employee15:Salary>$32,500</Employee15:Salary>
   </Employee15:emp>

   <Employee16:emp xmlns:Employee16="https://www.emp16.com">
      <Employee16:Name>Sarah Davis</Employee16:Name>
      <Employee16:Status>Fulltime</Employee16:Status>
      <Employee16:Department>Sales</Employee16:Department>
      <Employee16:Years>5</Employee16:Years>
      <Employee16:SS>378-96-3822</Employee16:SS>
      <Employee16:Health>Bonus Married</Employee16:Health>
      <Employee16:Salary>$52,500</Employee16:Salary>
   </Employee16:emp>

</Staff>